smtpcom/__init__.py
smtpcom/base_interface.py
smtpcom/client.py
smtpcom/exceptions.py
smtpcom/smtpcom.py
smtpcom/version.py
smtpcom/helpers/__init__.py
smtpcom/helpers/mail/__init__.py
smtpcom/helpers/mail/attachment.py
smtpcom/helpers/mail/bcc_email.py
smtpcom/helpers/mail/bulk_list.py
smtpcom/helpers/mail/cc_email.py
smtpcom/helpers/mail/channel.py
smtpcom/helpers/mail/content.py
smtpcom/helpers/mail/custom_headers.py
smtpcom/helpers/mail/email.py
smtpcom/helpers/mail/from_email.py
smtpcom/helpers/mail/header.py
smtpcom/helpers/mail/mail.py
smtpcom/helpers/mail/mime.py
smtpcom/helpers/mail/reply_to.py
smtpcom/helpers/mail/subject.py
smtpcom/helpers/mail/to_email.py
test/integration/__init__.py
test/integration/test_smtpcom.py
test/unit/__init__.py
test/unit/test_email.py
test/unit/test_mail.py
smtpcom-1.1.1.dist-info/LICENSE
smtpcom-1.1.1.dist-info/METADATA
smtpcom-1.1.1.dist-info/WHEEL
smtpcom-1.1.1.dist-info/top_level.txt
smtpcom-1.1.1.dist-info/RECORD
